[
    {
      "name": "Casa Bella Vista",
      "description": "A spacious house with a breathtaking view of the city.",
      "number_of_rooms": 5,
      "number_of_bathrooms": 3,
      "number_of_beds": 4,
      "square_meters": 150,
      "address": " Via Luigi Pirandello, 84, 98039 Taormina ME",
      "longitude": "15.296858744144192",
      "latitude": "37.84772130275286",
      "visibility": "",
      "image_cover": ""
    },
    {
      "name": "Villa Tranquilla",
      "description": "A tranquil villa surrounded by greenery.",
      "number_of_rooms": 6,
      "number_of_bathrooms": 4,
      "number_of_beds": 5,
      "square_meters": 200,
      "address": " Via Luigi Pirandello, 75, 98039 Taormina ME",
      "longitude": "15.29470930985784 ",
      "latitude": "37.85263650717436",
      "visibility": "",
      "image_cover": ""
    },
    {
      "name": "Central Apartment",
      "description": "A modern apartment located in the heart of the city.",
      "number_of_rooms": 3,
      "number_of_bathrooms": 2,
      "number_of_beds": 3,
      "square_meters": 85,
      "address": "Via Nazionale, 248, 98030 Taormina ME",
      "longitude": "15.297156919070908 ",
      "latitude": "37.85884854359011",
      "visibility": "",
      "image_cover": ""
    },
    {
      "name": "Rustic Cottage",
      "description": "A charming rustic-style cottage, perfect for a relaxing getaway.",
      "number_of_rooms": 4,
      "number_of_bathrooms": 2,
      "number_of_beds": 3,
      "square_meters": 120,
      "address": "Via Nazionale, 175, 98030 Taormina ME",
      "longitude": "15.295864093678093 ",
      "latitude": "37.861713661431224",
      "visibility": "",
      "image_cover": ""
    },
    {
      "name": "Luxury Residence",
      "description": "A luxurious residence with modern furnishings and high-quality finishes.",
      "number_of_rooms": 7,
      "number_of_bathrooms": 5,
      "number_of_beds": 6,
      "square_meters": 250,
      "address": " Via Bongiovanni, 2/A, 98039 Taormina ME",
      "longitude": "15.293382840021644",
      "latitude": "37.85486375784265,",
      "visibility": "",
      "image_cover": ""
    },
    {
      "name": "Lake House",
      "description": "A delightful house located on the shores of a serene lake.",
      "number_of_rooms": 4,
      "number_of_bathrooms": 3,
      "number_of_beds": 4,
      "square_meters": 130,
      "address": "Via Gaetano Martino, 13, 98039 Taormina ME",
      "longitude": "15.289156524759866 ",
      "latitude": "37.8594180019036",
      "visibility": "",
      "image_cover": ""
    },
    {
      "name": "Panoramic Penthouse",
      "description": "An elegant penthouse with a panoramic view of the city.",
      "number_of_rooms": 3,
      "number_of_bathrooms": 2,
      "number_of_beds": 2,
      "square_meters": 90,
      "address": " Vico Zecca, 3, 98039 Taormina ME",
      "longitude": "15.289132821307067 ",
      "latitude": "37.85462070198995",
      "visibility": "",
      "image_cover": ""
    },
    {
      "name": "Family House",
      "description": "A spacious and cozy house, ideal for large families.",
      "number_of_rooms": 6,
      "number_of_bathrooms": 4,
      "number_of_beds": 5,
      "square_meters": 180,
      "address": "Salita Giafari, 13, 98039 Taormina ME",
      "longitude": "15.28775699468085 ",
      "latitude": "37.85426044944567",
      "visibility": "",
      "image_cover": ""
    },
    {
      "name": "Beach Bungalow",
      "description": "A cozy bungalow located right on the beach.",
      "number_of_rooms": 3,
      "number_of_bathrooms": 2,
      "number_of_beds": 3,
      "square_meters": 100,
      "address": " Via Luigi Pirandello, 65/71, 98039 Taormina ME",
      "longitude": "15.292924742583885 ",
      "latitude": "37.85357770306747",
      "visibility": "",
      "image_cover": ""
    },
    {
      "name": "Mountain Chalet",
      "description": "A charming chalet situated in the mountains.",
      "number_of_rooms": 5,
      "number_of_bathrooms": 3,
      "number_of_beds": 4,
      "square_meters": 140,
      "address": "Via Silipigni, 7A, 98039 Taormina ME",
      "longitude": "15.288784011238832 ",
      "latitude": "37.85588673523153",
      "visibility": "",
      "image_cover": ""
    }
  ]
  